Metadata-Version: 1.0
Name: navy-first
Version: 0.1
Summary: navy  module
Home-page: UNKNOWN
Author: navy
Author-email: whj001@126.com
License: MIT
Platform: linux
